{
  "$schema": "https://zed.dev/schema/themes/v0.2.0.json",
  "name": "Thunky",
  "author": "Sebastian Nomme",
  "themes": [
    {
      "name": "Thunky (Dark)",
      "appearance": "dark",
      "style": {
        "border": "#A7A8B415",
        "border.variant": "#A7A8B415",
        "background": "#131316",
        "panel.background": "#131316",
        "tab_bar.background": "#131316",
        "tab.active_background": "#131316",
        "tab.inactive_background": "#ffffff08",
        "title_bar.background": "#131316",
        "toolbar.background": "#131316",
        "terminal.background": "#131316",
        "surface.background": "#131316",
        "scrollbar.track.border": "#ffffff20",
        "status_bar.background": "#131316",
        "editor.active_line.background": "#A7A8B415",
        "editor.background": "#131316",
        "editor.foreground": "#ffffff",
        "editor.line_number": "#ffffff32",
        "editor.gutter.background": "#131316",
        "editor.document_highlight.bracket_background": "#323438",
        "ghost_element.selected": "#A7A8B415",
        "ghost_element.background": "#ffffff08",
        "ghost_element.hover": "#A7A8B415",
        "created": "#409D78",
        "deleted": "#EC5D6F",
        "modified": "#CD984D",
        "syntax": {
          "attribute": {
            "color": "#af9cffff",
            "font_style": "normal",
            "font_weight": 400
          },
          "boolean": {
            "color": "#82d2ceff",
            "font_style": "normal",
            "font_weight": 400
          },
          "comment": {
            "color": "#898989ff",
            "font_style": "normal",
            "font_weight": 400
          },
          "comment.doc": {
            "color": "#898989ff",
            "font_style": "normal",
            "font_weight": 400
          },
          "constant": {
            "color": "#af9cffff",
            "font_style": "normal",
            "font_weight": 400
          },
          "enum": {
            "color": "#87c3ffff",
            "font_style": "normal",
            "font_weight": 400
          },
          "function": {
            "color": "#ebc88dff",
            "font_style": "normal",
            "font_weight": 400
          },
          "function.definition": {
            "color": "#efefef",
            "font_style": "normal",
            "font_weight": 600
          },
          "function.special": {
            "color": "#a8cc7cff",
            "font_style": "normal",
            "font_weight": 400
          },
          "function.special.definition": {
            "color": "#d1d1d1ff"
          },
          "keyword": {
            "color": "#82d2ceff",
            "font_style": "normal",
            "font_weight": 400
          },
          "link.text": {
            "color": null,
            "font_style": "normal",
            "font_weight": 400
          },
          "link.uri": {
            "color": "#add1deff",
            "font_style": "normal",
            "font_weight": 400
          },
          "number": {
            "color": "#ebc88dff",
            "font_style": "normal",
            "font_weight": 400
          },
          "operator": {
            "color": "#d1d1d1ff",
            "font_style": "normal",
            "font_weight": 400
          },
          "property": {
            "color": "#af9cffff",
            "font_style": "normal",
            "font_weight": 400
          },
          "property.json_key": {
            "color": "#82d2ceff",
            "font_style": "normal",
            "font_weight": 400
          },
          "punctuation.bracket": {
            "color": "#d1d1d1ff",
            "font_style": "normal",
            "font_weight": 400
          },
          "string": {
            "color": "#e394dcff",
            "font_style": "normal",
            "font_weight": 400
          },
          "string.escape": {
            "color": "#82d2ceff",
            "font_style": "normal",
            "font_weight": 400
          },
          "string.regex": {
            "color": "#82d2ceff",
            "font_style": "normal",
            "font_weight": 400
          },
          "string.special": {
            "color": "#82d2ceff",
            "font_style": "normal",
            "font_weight": 400
          },
          "string.special.symbol": {
            "color": "#af9cffff",
            "font_style": "normal",
            "font_weight": 400
          },
          "tag": {
            "color": "#87c3ffff",
            "font_style": "normal",
            "font_weight": 400
          },
          "text.literal": {
            "color": "#e394dcff",
            "font_style": "normal",
            "font_weight": 400
          },
          "type": {
            "color": "#87c3ffff",
            "font_style": "normal",
            "font_weight": 400
          },
          "type.builtin": {
            "color": "#82d2ceff",
            "font_style": "normal",
            "font_weight": 400
          },
          "variable": {
            "color": "#d1d1d1ff",
            "font_style": "normal",
            "font_weight": 400
          },
          "variable.special": {
            "color": "#cc7c8aff",
            "font_style": "normal",
            "font_weight": 400
          }
        }
      }
    }
  ]
}
